Workbook
Name Slicer_Account: #N/A
Name Slicer_Department: #N/A
Name Slicer_Months__Date: #N/A

Sheet Actuals
A1: Date | B1: Department | C1: Account | D1: Actual_Amount | E1: Category
A2: 45292 | B2: Sales | C2: Product Revenue | D2: 11965 | E2: =VLOOKUP(Actual_Table[[#This Row],[Account]],#REF!,2,FALSE) -> #REF!
A3: 45292 | B3: Sales | C3: Service Revenue | D3: 13096 | E3: =VLOOKUP(Actual_Table[[#This Row],[Account]],#REF!,2,FALSE) -> #REF!
A4: 45292 | B4: Sales | C4: Salaries | D4: 13253 | E4: =VLOOKUP(Actual_Table[[#This Row],[Account]],#REF!,2,FALSE) -> #REF!
A5: 45292 | B5: Sales | C5: Rent | D5: 2949 | E5: =VLOOKUP(Actual_Table[[#This Row],[Account]],#REF!,2,FALSE) -> #REF!
A6: 45292 | B6: Sales | C6: Marketing Spend | D6: 4445 | E6: =VLOOKUP(Actual_Table[[#This Row],[Account]],#REF!,2,FALSE) -> #REF!
A7: 45292 | B7: Sales | C7: Software Licenses | D7: 21588 | E7: =VLOOKUP(Actual_Table[[#This Row],[Account]],#REF!,2,FALSE) -> #REF!
A8: 45292 | B8: Marketing | C8: Product Revenue | D8: 19298 | E8: =VLOOKUP(Actual_Table[[#This Row],[Account]],#REF!,2,FALSE) -> #REF!
A9: 45292 | B9: Marketing | C9: Service Revenue | D9: 6289 | E9: =VLOOKUP(Actual_Table[[#This Row],[Account]],#REF!,2,FALSE) -> #REF!
A10: 45292 | B10: Marketing | C10: Salaries | D10: 19754 | E10: =VLOOKUP(Actual_Table[[#This Row],[Account]],#REF!,2,FALSE) -> #REF!
A11: 45292 | B11: Marketing | C11: Rent | D11: 7772 | E11: =VLOOKUP(Actual_Table[[#This Row],[Account]],#REF!,2,FALSE) -> #REF!
A12: 45292 | B12: Marketing | C12: Marketing Spend | D12: 12346 | E12: =VLOOKUP(Actual_Table[[#This Row],[Account]],#REF!,2,FALSE) -> #REF!
A13: 45292 | B13: Marketing | C13: Software Licenses | D13: 1087 | E13: =VLOOKUP(Actual_Table[[#This Row],[Account]],#REF!,2,FALSE) -> #REF!
... A10981: 45657 | B10981: HR | C10981: Software Licenses | D10981: 15954 | E10981: =VLOOKUP(Actual_Table[[#This Row],[Account]],#REF!,2,FALSE) -> #REF!

Sheet Budgets
A1: Date | B1: Department | C1: Account | D1: Budget_Amount | E1: Category
A2: 45292 | B2: Sales | C2: Product Revenue | D2: 10810 | E2: =VLOOKUP(Budget_Table[[#This Row],[Account]],#REF!,2,FALSE) -> #REF!
A3: 45292 | B3: Sales | C3: Service Revenue | D3: 14344 | E3: =VLOOKUP(Budget_Table[[#This Row],[Account]],#REF!,2,FALSE) -> #REF!
A4: 45292 | B4: Sales | C4: Salaries | D4: 15431 | E4: =VLOOKUP(Budget_Table[[#This Row],[Account]],#REF!,2,FALSE) -> #REF!
A5: 45292 | B5: Sales | C5: Rent | D5: 2864 | E5: =VLOOKUP(Budget_Table[[#This Row],[Account]],#REF!,2,FALSE) -> #REF!
A6: 45292 | B6: Sales | C6: Marketing Spend | D6: 4451 | E6: =VLOOKUP(Budget_Table[[#This Row],[Account]],#REF!,2,FALSE) -> #REF!
A7: 45292 | B7: Sales | C7: Software Licenses | D7: 23766 | E7: =VLOOKUP(Budget_Table[[#This Row],[Account]],#REF!,2,FALSE) -> #REF!
A8: 45292 | B8: Marketing | C8: Product Revenue | D8: 19069 | E8: =VLOOKUP(Budget_Table[[#This Row],[Account]],#REF!,2,FALSE) -> #REF!
A9: 45292 | B9: Marketing | C9: Service Revenue | D9: 4493 | E9: =VLOOKUP(Budget_Table[[#This Row],[Account]],#REF!,2,FALSE) -> #REF!
A10: 45292 | B10: Marketing | C10: Salaries | D10: 17595 | E10: =VLOOKUP(Budget_Table[[#This Row],[Account]],#REF!,2,FALSE) -> #REF!
A11: 45292 | B11: Marketing | C11: Rent | D11: 8871 | E11: =VLOOKUP(Budget_Table[[#This Row],[Account]],#REF!,2,FALSE) -> #REF!
A12: 45292 | B12: Marketing | C12: Marketing Spend | D12: 13961 | E12: =VLOOKUP(Budget_Table[[#This Row],[Account]],#REF!,2,FALSE) -> #REF!
A13: 45292 | B13: Marketing | C13: Software Licenses | D13: -898 | E13: =VLOOKUP(Budget_Table[[#This Row],[Account]],#REF!,2,FALSE) -> #REF!
... A10981: 45657 | B10981: HR | C10981: Software Licenses | D10981: 13084 | E10981: =VLOOKUP(Budget_Table[[#This Row],[Account]],#REF!,2,FALSE) -> #REF!

Sheet Actual vs Budget by Department
B2: Department | C2: Actual | D2: Budget
B3: Finance | C3: 27583339 | D3: 27653717
B4: HR | C4: 27782343 | D4: 27766026
B5: IT | C5: 27755887 | D5: 27756582
B6: Marketing | C6: 28102305 | D6: 28067885
B7: Sales | C7: 27876586 | D7: 27774393

Sheet Monthly Performance Trend
A4: Months | B4: Actual | C4: Budget
A5: 2024 | B5: 139100460 | C5: 139018603
A6: Jan | B6: 11623834 | C6: 11587421
A7: Feb | B7: 10863238 | C7: 10893796
A8: Mar | B8: 11744808 | C8: 11726819
A9: Apr | B9: 11414372 | C9: 11375397
A10: May | B10: 11745591 | C10: 11690350
A11: Jun | B11: 11381047 | C11: 11431343
A12: Jul | B12: 11736480 | C12: 11765792
A13: Aug | B13: 11952114 | C13: 11864602
A14: Sep | B14: 11770007 | C14: 11722024
A15: Oct | B15: 11842134 | C15: 11903192
A16: Nov | B16: 11397593 | C16: 11366244
A17: Dec | B17: 11629242 | C17: 11691623

Sheet Model_Data 
A1: {=_xlfn.VSTACK(Actual_Table[[#All],[Date]:[Actual_Amount]])} -> Date | B1: Department | C1: Account | D1: Actual_Amount | E1: {=_xlfn.VSTACK(Budget_Table[[#All],[Date]:[Budget_Amount]])} -> Date | F1: Department | G1: Account | H1: Budget_Amount
A2: 45292 | B2: Sales | C2: Product Revenue | D2: 11965 | E2: 45292 | F2: Sales | G2: Product Revenue | H2: 10810
A3: 45292 | B3: Sales | C3: Service Revenue | D3: 13096 | E3: 45292 | F3: Sales | G3: Service Revenue | H3: 14344
A4: 45292 | B4: Sales | C4: Salaries | D4: 13253 | E4: 45292 | F4: Sales | G4: Salaries | H4: 15431
A5: 45292 | B5: Sales | C5: Rent | D5: 2949 | E5: 45292 | F5: Sales | G5: Rent | H5: 2864
A6: 45292 | B6: Sales | C6: Marketing Spend | D6: 4445 | E6: 45292 | F6: Sales | G6: Marketing Spend | H6: 4451
A7: 45292 | B7: Sales | C7: Software Licenses | D7: 21588 | E7: 45292 | F7: Sales | G7: Software Licenses | H7: 23766
A8: 45292 | B8: Marketing | C8: Product Revenue | D8: 19298 | E8: 45292 | F8: Marketing | G8: Product Revenue | H8: 19069
A9: 45292 | B9: Marketing | C9: Service Revenue | D9: 6289 | E9: 45292 | F9: Marketing | G9: Service Revenue | H9: 4493
A10: 45292 | B10: Marketing | C10: Salaries | D10: 19754 | E10: 45292 | F10: Marketing | G10: Salaries | H10: 17595
A11: 45292 | B11: Marketing | C11: Rent | D11: 7772 | E11: 45292 | F11: Marketing | G11: Rent | H11: 8871
A12: 45292 | B12: Marketing | C12: Marketing Spend | D12: 12346 | E12: 45292 | F12: Marketing | G12: Marketing Spend | H12: 13961
A13: 45292 | B13: Marketing | C13: Software Licenses | D13: 1087 | E13: 45292 | F13: Marketing | G13: Software Licenses | H13: -898
... A10981: 45657 | B10981: HR | C10981: Software Licenses | D10981: 15954 | E10981: 45657 | F10981: HR | G10981: Software Licenses | H10981: 13084

Sheet Account Summary
A1: Sum of Amount | B1: Column Labels
A2: Row Labels | B2: Actual | C2: Budget | E2: Department | F2: Account | G2: Actual | H2: Budget | I2: Variance. | J2: Variance %.
A3: Marketing Spend | B3: 23291597 | C3: 23203451 | E3: Finance | F3: Marketing Spend | G3: 4538882 | H3: 4524265 | I3: -14617 | J3: -0.003230801
A4: Product Revenue | B4: 22977820 | C4: 22997018 | F4: Product Revenue | G4: 4508541 | H4: 4522141 | I4: 13600 | J4: 0.003007425
A5: Rent | B5: 23330510 | C5: 23332323 | F5: Rent | G5: 4727798 | H5: 4741598 | I5: 13800 | J5: 0.0029104112
A6: Salaries | B6: 23333333 | C6: 23358211 | F6: Salaries | G6: 4575381 | H6: 4613870 | I6: 38489 | J6: 0.0083420209
A7: Service Revenue | B7: 22817687 | C7: 22799843 | F7: Service Revenue | G7: 4618889 | H7: 4604368 | I7: -14521 | J7: -0.0031537444
A8: Software Licenses | B8: 23349513 | C8: 23327757 | F8: Software Licenses | G8: 4613848 | H8: 4647475 | I8: 33627 | J8: 0.0072355419
E9: HR | F9: Marketing Spend | G9: 4604580 | H9: 4598664 | I9: -5916 | J9: -0.0012864606
F10: Product Revenue | G10: 4622558 | H10: 4651473 | I10: 28915 | J10: 0.0062163104
F11: Rent | G11: 4722884 | H11: 4733591 | I11: 10707 | J11: 0.0022619191
F12: Salaries | G12: 4634832 | H12: 4613858 | I12: -20974 | J12: -0.0045458703
A13: Unique Department List | B13: Unique Account List | F13: Service Revenue | G13: 4575802 | H13: 4533243 | I13: -42559 | J13: -0.0093882018
A14: {=_xlfn.UNIQUE(Actual_Table[Department],FALSE,FALSE)} -> Sales | B14: {=_xlfn.UNIQUE(Actual_Table[Account],FALSE,FALSE)} -> Product Revenue | F14: Software Licenses | G14: 4621687 | H14: 4635197 | I14: 13510 | J14: 0.002914655
A15: Marketing | B15: Service Revenue | E15: IT | F15: Marketing Spend | G15: 4573341 | H15: 4528155 | I15: -45186 | J15: -0.0099788987
A16: Finance | B16: Salaries | F16: Product Revenue | G16: 4521241 | H16: 4542262 | I16: 21021 | J16: 0.0046278704
A17: IT | B17: Rent | F17: Rent | G17: 4613257 | H17: 4631234 | I17: 17977 | J17: 0.0038816868
A18: HR | B18: Marketing Spend | F18: Salaries | G18: 4835319 | H18: 4843860 | I18: 8541 | J18: 0.0017632632
B19: Software Licenses | F19: Service Revenue | G19: 4493595 | H19: 4500175 | I19: 6580 | J19: 0.0014621654
F20: Software Licenses | G20: 4719134 | H20: 4710896 | I20: -8238 | J20: -0.0017487119
E21: Marketing | F21: Marketing Spend | G21: 4879170 | H21: 4872266 | I21: -6904 | J21: -0.0014169998
F22: Product Revenue | G22: 4560417 | H22: 4548433 | I22: -11984 | J22: -0.0026347536
F23: Rent | G23: 4456248 | H23: 4441246 | I23: -15002 | J23: -0.0033778809
F24: Salaries | G24: 4671464 | H24: 4651744 | I24: -19720 | J24: -0.0042392703
F25: Service Revenue | G25: 4627946 | H25: 4691810 | I25: 63864 | J25: 0.013611804
F26: Software Licenses | G26: 4907060 | H26: 4862386 | I26: -44674 | J26: -0.0091876704
E27: Sales | F27: Marketing Spend | G27: 4695624 | H27: 4680101 | I27: -15523 | J27: -0.0033168088
F28: Product Revenue | G28: 4765063 | H28: 4732709 | I28: -32354 | J28: -0.0068362538
F29: Rent | G29: 4810323 | H29: 4784654 | I29: -25669 | J29: -0.0053648602
F30: Salaries | G30: 4616337 | H30: 4634879 | I30: 18542 | J30: 0.0040005359
F31: Service Revenue | G31: 4501455 | H31: 4470247 | I31: -31208 | J31: -0.0069812697
F32: Software Licenses | G32: 4487784 | H32: 4471803 | I32: -15981 | J32: -0.0035737263
E33: Grand Total | G33: 139100460 | H33: 139018603 | I33: -81857 | J33: -0.00058882048

Sheet Variance by Department 
A1: Row Labels | B1: Sum of Variance
A2: Finance | B2: 70378
A3: HR | B3: -16317
A4: IT | B4: 695
A5: Marketing | B5: -34420
A6: Sales | B6: -102193
A7: Grand Total | B7: -81857

Sheet Dashboard
S2: Actual | T2: Budget | U2: Variance | V2: Variance%
S3: =GETPIVOTDATA("Actual",'Account Summary'!$E$2) -> 139100460 | T3: =GETPIVOTDATA("Budget",'Account Summary'!$E$2) -> 139018603 | U3: =GETPIVOTDATA("Variance.",'Account Summary'!$E$2) -> -81857 | V3: =GETPIVOTDATA("Variance %.",'Account Summary'!$E$2) -> -0.00058882048
S6: Best Dept
S7: =MAX('Variance by Department '!B2:B6) -> 70378
S8: Worst Dept
S9: =MIN('Variance by Department '!B2:B6) -> -102193
K12: Accounts Summary
K13: Accounts | L13: Budget | M13: Actual | N13: Variance.
K14: Accounts | L14: Budget | M14: Actual | N14: Variance.
K15: Salaries | L15: 23358211 | M15: 23333333 | N15: 24878
K16: Product Revenue | L16: 22997018 | M16: 22977820 | N16: 19198
K17: Rent | L17: 23332323 | M17: 23330510 | N17: 1813
K18: Service Revenue | L18: 22799843 | M18: 22817687 | N18: -17844
K19: Software Licenses | L19: 23327757 | M19: 23349513 | N19: -21756
K20: Marketing Spend | L20: 23203451 | M20: 23291597 | N20: -88146
K21: Grand Total | L21: 139018603 | M21: 139100460 | N21: -81857
